winrt_sdk/__init__.py
winrt_sdk/cppwinrt/winrt/Windows.AI.Actions.Hosting.h
winrt_sdk/cppwinrt/winrt/Windows.AI.Actions.Provider.h
winrt_sdk/cppwinrt/winrt/Windows.AI.Actions.h
winrt_sdk/cppwinrt/winrt/Windows.AI.MachineLearning.Preview.h
winrt_sdk/cppwinrt/winrt/Windows.AI.MachineLearning.h
winrt_sdk/cppwinrt/winrt/Windows.AI.ModelContextProtocol.h
winrt_sdk/cppwinrt/winrt/Windows.ApplicationModel.Activation.h
winrt_sdk/cppwinrt/winrt/Windows.ApplicationModel.AppExtensions.h
winrt_sdk/cppwinrt/winrt/Windows.ApplicationModel.AppService.h
winrt_sdk/cppwinrt/winrt/Windows.ApplicationModel.Appointments.AppointmentsProvider.h
winrt_sdk/cppwinrt/winrt/Windows.ApplicationModel.Appointments.DataProvider.h
winrt_sdk/cppwinrt/winrt/Windows.ApplicationModel.Appointments.h
winrt_sdk/cppwinrt/winrt/Windows.ApplicationModel.Background.h
winrt_sdk/cppwinrt/winrt/Windows.ApplicationModel.Calls.Background.h
winrt_sdk/cppwinrt/winrt/Windows.ApplicationModel.Calls.Provider.h
winrt_sdk/cppwinrt/winrt/Windows.ApplicationModel.Calls.h
winrt_sdk/cppwinrt/winrt/Windows.ApplicationModel.Chat.h
winrt_sdk/cppwinrt/winrt/Windows.ApplicationModel.CommunicationBlocking.h
winrt_sdk/cppwinrt/winrt/Windows.ApplicationModel.Contacts.DataProvider.h
winrt_sdk/cppwinrt/winrt/Windows.ApplicationModel.Contacts.Provider.h
winrt_sdk/cppwinrt/winrt/Windows.ApplicationModel.Contacts.h
winrt_sdk/cppwinrt/winrt/Windows.ApplicationModel.ConversationalAgent.h
winrt_sdk/cppwinrt/winrt/Windows.ApplicationModel.Core.h
winrt_sdk/cppwinrt/winrt/Windows.ApplicationModel.DataTransfer.DragDrop.Core.h
winrt_sdk/cppwinrt/winrt/Windows.ApplicationModel.DataTransfer.DragDrop.h
winrt_sdk/cppwinrt/winrt/Windows.ApplicationModel.DataTransfer.ShareTarget.h
winrt_sdk/cppwinrt/winrt/Windows.ApplicationModel.DataTransfer.h
winrt_sdk/cppwinrt/winrt/Windows.ApplicationModel.Email.DataProvider.h
winrt_sdk/cppwinrt/winrt/Windows.ApplicationModel.Email.h
winrt_sdk/cppwinrt/winrt/Windows.ApplicationModel.ExtendedExecution.Foreground.h
winrt_sdk-3.2.1.dist-info/METADATA
winrt_sdk-3.2.1.dist-info/WHEEL
winrt_sdk-3.2.1.dist-info/top_level.txt
winrt_sdk-3.2.1.dist-info/RECORD
